nion/eels_analysis/BackgroundModel.py
nion/eels_analysis/CurveFitting.py
nion/eels_analysis/CurveFittingAndAnalysis.py
nion/eels_analysis/EELS_CrossSections.py
nion/eels_analysis/EELS_DataAnalysis.py
nion/eels_analysis/EELS_EdgeIdentification.py
nion/eels_analysis/PeakModel.py
nion/eels_analysis/PeriodicTable.py
nion/eels_analysis/ZLP_Analysis.py
nion/eels_analysis/__init__.py
nion/eels_analysis/eels_analysis.py
nion/eels_analysis/resources/edges.json
nion/eels_analysis/test/CoreLossEdge_test.py
nion/eels_analysis/test/EELSAnalysisFunctions_test.py
nion/eels_analysis/test/PeriodicTable_test.py
nion/eels_analysis/test/ZLP_analysis_test.py
nion/eels_analysis/test/__init__.py
nionswift_eels_analysis-0.6.13.dist-info/licenses/LICENSE
nionswift_plugin/nion_eels_analysis/AlignZLP.py
nionswift_plugin/nion_eels_analysis/BackgroundSubtraction.py
nionswift_plugin/nion_eels_analysis/ElementalMappingController.py
nionswift_plugin/nion_eels_analysis/ElementalMappingPanel.py
nionswift_plugin/nion_eels_analysis/LiveThickness.py
nionswift_plugin/nion_eels_analysis/LiveZLP.py
nionswift_plugin/nion_eels_analysis/PeakFitting.py
nionswift_plugin/nion_eels_analysis/Thermometry.py
nionswift_plugin/nion_eels_analysis/ThicknessMap.py
nionswift_plugin/nion_eels_analysis/__init__.py
nionswift_plugin/nion_eels_analysis/resources/color_maps/sqe_bgyw.xml
nionswift_plugin/nion_eels_analysis/test/AlignZLP_test.py
nionswift_plugin/nion_eels_analysis/test/Analysis_test.py
nionswift_plugin/nion_eels_analysis/test/BackgroundSubtraction_test.py
nionswift_plugin/nion_eels_analysis/test/ElementalMapping_test.py
nionswift_plugin/nion_eels_analysis/test/PeakFitting_test.py
nionswift_plugin/nion_eels_analysis/test/__init__.py
nionswift_eels_analysis-0.6.13.dist-info/METADATA
nionswift_eels_analysis-0.6.13.dist-info/WHEEL
nionswift_eels_analysis-0.6.13.dist-info/top_level.txt
nionswift_eels_analysis-0.6.13.dist-info/RECORD
