Metadata-Version: 2.4
Name: nionswift-eels-analysis
Version: 0.6.13
Summary: Library and UI for doing EELS analysis with Nion Swift.
Home-page: https://github.com/nion-software/eels-analysis
Author: Nion Software
Author-email: swift@nion.com
License: GPL-3.0-only
Classifier: Development Status :: 4 - Beta
Classifier: License :: OSI Approved :: GNU General Public License v3 (GPLv3)
Classifier: Programming Language :: Python :: 3.11
Classifier: Programming Language :: Python :: 3.12
Classifier: Programming Language :: Python :: 3.13
Requires-Python: >=3.11
License-File: LICENSE
Requires-Dist: nionswift<17.0,>=16.16
Requires-Dist: nionui<11.0,>=10.2
Requires-Dist: numpy<3.0,>=2.0
Dynamic: license-file
